cartesia_mcp/__init__.py
cartesia_mcp/server.py
cartesia_mcp/utils.py
cartesia_mcp/custom_types/__init__.py
cartesia_mcp/custom_types/tool_results.py
cartesia_mcp/custom_types/tool_type.py
iflow_mcp_cartesia_ai_cartesia_mcp-0.1.6.dist-info/METADATA
iflow_mcp_cartesia_ai_cartesia_mcp-0.1.6.dist-info/WHEEL
iflow_mcp_cartesia_ai_cartesia_mcp-0.1.6.dist-info/entry_points.txt
iflow_mcp_cartesia_ai_cartesia_mcp-0.1.6.dist-info/top_level.txt
iflow_mcp_cartesia_ai_cartesia_mcp-0.1.6.dist-info/RECORD
