Metadata-Version: 2.4
Name: iflow-mcp_cartesia-ai_cartesia-mcp
Version: 0.1.6
Summary: The official Cartesia MCP server
Requires-Python: >=3.11
Requires-Dist: cartesia>=2.0.2
Requires-Dist: httpx>=0.28.1
Requires-Dist: mcp[cli]>=1.7.1
